xgboost/VERSION
xgboost/__init__.py
xgboost/_data_utils.py
xgboost/_typing.py
xgboost/callback.py
xgboost/collective.py
xgboost/compat.py
xgboost/config.py
xgboost/core.py
xgboost/data.py
xgboost/federated.py
xgboost/libpath.py
xgboost/plotting.py
xgboost/py.typed
xgboost/sklearn.py
xgboost/tracker.py
xgboost/training.py
xgboost/dask/__init__.py
xgboost/dask/data.py
xgboost/dask/utils.py
xgboost/lib/libxgboost.so
xgboost/spark/__init__.py
xgboost/spark/core.py
xgboost/spark/data.py
xgboost/spark/estimator.py
xgboost/spark/params.py
xgboost/spark/summary.py
xgboost/spark/utils.py
xgboost/testing/__init__.py
xgboost/testing/basic_models.py
xgboost/testing/callbacks.py
xgboost/testing/collective.py
xgboost/testing/continuation.py
xgboost/testing/dask.py
xgboost/testing/data.py
xgboost/testing/data_iter.py
xgboost/testing/federated.py
xgboost/testing/interaction_constraints.py
xgboost/testing/metrics.py
xgboost/testing/monotone_constraints.py
xgboost/testing/ordinal.py
xgboost/testing/params.py
xgboost/testing/parse_tree.py
xgboost/testing/plotting.py
xgboost/testing/predict.py
xgboost/testing/quantile_dmatrix.py
xgboost/testing/ranking.py
xgboost/testing/shared.py
xgboost/testing/updater.py
xgboost/testing/utils.py
xgboost/testing/with_skl.py
xgboost_cpu.libs/libgomp-a49a47f9.so.1.0.0
xgboost_cpu-3.1.0.dist-info/METADATA
xgboost_cpu-3.1.0.dist-info/WHEEL
xgboost_cpu-3.1.0.dist-info/RECORD
